Workbook
Name UPDATE: 'Data Sheet'!$E$1

Sheet Profit & Loss
A1: ='Data Sheet'!B1 -> BAJAJ AUTO LTD | H1: =UPDATE
A3: Narration | B3: ='Data Sheet'!B16 -> 42094 | C3: ='Data Sheet'!C16 -> 42460 | D3: ='Data Sheet'!D16 -> 42825 | E3: ='Data Sheet'!E16 -> 43190 | F3: ='Data Sheet'!F16 -> 43555 | G3: ='Data Sheet'!G16 -> 43921 | H3: ='Data Sheet'!H16 -> 44286 | I3: ='Data Sheet'!I16 -> 44651 | ... K3: ='Data Sheet'!K16 -> 45382 | L3: Trailing | M3: Best Case | N3: Worst Case
A4: Sales | B4: ='Data Sheet'!B17 -> 21595.44 | C4: ='Data Sheet'!C17 -> 22573.69 | D4: ='Data Sheet'!D17 -> 21754.72 | E4: ='Data Sheet'!E17 -> 25209.93 | F4: ='Data Sheet'!F17 -> 30357.63 | G4: ='Data Sheet'!G17 -> 29918.65 | H4: ='Data Sheet'!H17 -> 27741.08 | I4: ='Data Sheet'!I17 -> 33144.71 | ... K4: ='Data Sheet'!K17 -> 44870.43 | L4: =SUM(Quarters!H4:K4) -> 49903.18 | M4: =$K4+M23*K4 -> 55227.939 | N4: =$K4+N23*L4 -> 48926.598
A5: Expenses | B5: =SUM('Data Sheet'!B18,'Data Sheet'!B20:B24, -1*'Data Sheet'!B19) -> 17467.04 | C5: =SUM('Data Sheet'!C18,'Data Sheet'!C20:C24, -1*'Data Sheet'!C19) -> 17780.74 | D5: =SUM('Data Sheet'!D18,'Data Sheet'!D20:D24, -1*'Data Sheet'!D19) -> 17326.09 | E5: =SUM('Data Sheet'!E18,'Data Sheet'!E20:E24, -1*'Data Sheet'!E19) -> 20364.13 | F5: =SUM('Data Sheet'!F18,'Data Sheet'!F20:F24, -1*'Data Sheet'!F19) -> 25159.71 | G5: =SUM('Data Sheet'!G18,'Data Sheet'!G20:G24, -1*'Data Sheet'!G19) -> 24809.31 | H5: =SUM('Data Sheet'!H18,'Data Sheet'!H20:H24, -1*'Data Sheet'!H19) -> 22803.3 | I5: =SUM('Data Sheet'!I18,'Data Sheet'!I20:I24, -1*'Data Sheet'!I19) -> 27885.91 | ... K5: =SUM('Data Sheet'!K18,'Data Sheet'!K20:K24, -1*'Data Sheet'!K19) -> 36105.75 | L5: =SUM(Quarters!H5:K5) -> 40424.42 | M5: =M4-M6 -> 44737.778 | N5: =N4-N6 -> 40247.209
A6: Operating Profit | B6: =B4-B5 -> 4128.4 | C6: =C4-C5 -> 4792.95 | D6: =D4-D5 -> 4428.63 | E6: =E4-E5 -> 4845.8 | F6: =F4-F5 -> 5197.92 | G6: =G4-G5 -> 5109.34 | H6: =H4-H5 -> 4937.78 | I6: =I4-I5 -> 5258.8 | ... K6: =K4-K5 -> 8764.68 | L6: =SUM(Quarters!H6:K6) -> 9478.76 | M6: =M4*M24 -> 10490.161 | N6: =N4*N24 -> 8679.3891
A7: Other Income | B7: ='Data Sheet'!B25 -> 228.5 | C7: ='Data Sheet'!C25 -> 1194.15 | D7: ='Data Sheet'!D25 -> 1467.61 | E7: ='Data Sheet'!E25 -> 1403.72 | F7: ='Data Sheet'!F25 -> 2027.83 | G7: ='Data Sheet'!G25 -> 1832.38 | H7: ='Data Sheet'!H25 -> 1569.68 | I7: ='Data Sheet'!I25 -> 2671.3 | ... K7: ='Data Sheet'!K25 -> 1700.49 | L7: =SUM(Quarters!H7:K7) -> 1526.11 | M7: 0 | N7: 0
A8: Depreciation | B8: ='Data Sheet'!B26 -> 267.46 | C8: ='Data Sheet'!C26 -> 307.16 | D8: ='Data Sheet'!D26 -> 307.29 | E8: ='Data Sheet'!E26 -> 314.8 | F8: ='Data Sheet'!F26 -> 265.69 | G8: ='Data Sheet'!G26 -> 246.43 | H8: ='Data Sheet'!H26 -> 259.37 | I8: ='Data Sheet'!I26 -> 269.76 | ... K8: ='Data Sheet'!K26 -> 364.77 | L8: =SUM(Quarters!H8:K8) -> 387.81 | M8: =+$L8 -> 387.81 | N8: =+$L8 -> 387.81
A9: Interest | B9: ='Data Sheet'!B27 -> 6.49 | C9: ='Data Sheet'!C27 -> 1.05 | D9: ='Data Sheet'!D27 -> 1.4 | E9: ='Data Sheet'!E27 -> 1.31 | F9: ='Data Sheet'!F27 -> 4.48 | G9: ='Data Sheet'!G27 -> 3.16 | H9: ='Data Sheet'!H27 -> 6.66 | I9: ='Data Sheet'!I27 -> 8.66 | ... K9: ='Data Sheet'!K27 -> 60.36 | L9: =SUM(Quarters!H9:K9) -> 272.01 | M9: =+$L9 -> 272.01 | N9: =+$L9 -> 272.01
A10: Profit before tax | B10: ='Data Sheet'!B28 -> 4082.95 | C10: ='Data Sheet'!C28 -> 5678.89 | D10: ='Data Sheet'!D28 -> 5587.55 | E10: ='Data Sheet'!E28 -> 5933.41 | F10: ='Data Sheet'!F28 -> 6955.58 | G10: ='Data Sheet'!G28 -> 6692.13 | H10: ='Data Sheet'!H28 -> 6241.43 | I10: ='Data Sheet'!I28 -> 7651.68 | ... K10: ='Data Sheet'!K28 -> 10040.04 | L10: =SUM(Quarters!H10:K10) -> 10345.05 | M10: =M6+M7-SUM(M8:M9) -> 9830.3407 | N10: =N6+N7-SUM(N8:N9) -> 8019.5691
A11: Tax | B11: ='Data Sheet'!B29 -> 1271.05 | C11: ='Data Sheet'!C29 -> 1617.65 | D11: ='Data Sheet'!D29 -> 1508.07 | E11: ='Data Sheet'!E29 -> 1714.47 | F11: ='Data Sheet'!F29 -> 2027.98 | G11: ='Data Sheet'!G29 -> 1480.22 | H11: ='Data Sheet'!H29 -> 1384.41 | I11: ='Data Sheet'!I29 -> 1485.81 | ... K11: ='Data Sheet'!K29 -> 2331.8 | L11: =SUM(Quarters!H11:K11) -> 2810.74 | M11: =IF($L10>0,$L11/$L10,0) -> 0.27169903 | N11: =IF($L10>0,$L11/$L10,0) -> 0.27169903
A12: Net profit | B12: ='Data Sheet'!B30 -> 3025.63 | C12: ='Data Sheet'!C30 -> 4061.24 | D12: ='Data Sheet'!D30 -> 4079.49 | E12: ='Data Sheet'!E30 -> 4218.95 | F12: ='Data Sheet'!F30 -> 4927.61 | G12: ='Data Sheet'!G30 -> 5211.91 | H12: ='Data Sheet'!H30 -> 4857.02 | I12: ='Data Sheet'!I30 -> 6165.87 | ... K12: ='Data Sheet'!K30 -> 7708.24 | L12: =SUM(Quarters!H12:K12) -> 7534.31 | M12: =M10-M11*M10 -> 7159.4467 | N12: =N10-N11*N10 -> 5840.66
A13: EPS | B13: =IF('Data Sheet'!B93>0,B12/'Data Sheet'!B93,0) -> 104.54838 | C13: =IF('Data Sheet'!C93>0,C12/'Data Sheet'!C93,0) -> 140.3331 | D13: =IF('Data Sheet'!D93>0,D12/'Data Sheet'!D93,0) -> 140.96372 | E13: =IF('Data Sheet'!E93>0,E12/'Data Sheet'!E93,0) -> 145.78265 | F13: =IF('Data Sheet'!F93>0,F12/'Data Sheet'!F93,0) -> 170.26987 | G13: =IF('Data Sheet'!G93>0,G12/'Data Sheet'!G93,0) -> 180.09364 | H13: =IF('Data Sheet'!H93>0,H12/'Data Sheet'!H93,0) -> 167.83068 | I13: =IF('Data Sheet'!I93>0,I12/'Data Sheet'!I93,0) -> 213.05701 | ... K13: =IF('Data Sheet'!K93>0,K12/'Data Sheet'!K93,0) -> 276.08309 | L13: =IF('Data Sheet'!$B6>0,'Profit & Loss'!L12/'Data Sheet'!$B6,0) -> 269.78943 | M13: =IF('Data Sheet'!$B6>0,'Profit & Loss'!M12/'Data Sheet'!$B6,0) -> 256.36629 | N13: =IF('Data Sheet'!$B6>0,'Profit & Loss'!N12/'Data Sheet'!$B6,0) -> 209.14302
A14: Price to earning | B14: =IF(B15>0,B15/B13,"") -> 19.288678 | C14: =IF(C15>0,C15/C13,"") -> 17.144565 | D14: =IF(D15>0,D15/D13,"") -> 19.90193 | E14: =IF(E15>0,E15/E13,"") -> 18.827343 | F14: =IF(F15>0,F15/F13,"") -> 17.096977 | G14: =IF(G15>0,G15/G13,"") -> 11.229436 | H14: =IF(H15>0,H15/H13,"") -> 21.870852 | I14: =IF(I15>0,I15/I13,"") -> 17.145645 | ... K14: =IF(K15>0,K15/K13,"") -> 33.135495 | L14: =IF(L13>0,L15/L13,0) -> 30.570137 | M14: =M25 -> 30.570137 | N14: =N25 -> 20.395644
A15: Price | B15: ='Data Sheet'!B90 -> 2016.6 | C15: ='Data Sheet'!C90 -> 2405.95 | D15: ='Data Sheet'!D90 -> 2805.45 | E15: ='Data Sheet'!E90 -> 2744.7 | F15: ='Data Sheet'!F90 -> 2911.1 | G15: ='Data Sheet'!G90 -> 2022.35 | H15: ='Data Sheet'!H90 -> 3670.6 | I15: ='Data Sheet'!I90 -> 3653 | ... K15: ='Data Sheet'!K90 -> 9148.15 | L15: ='Data Sheet'!B8 -> 8247.5 | M15: =M13*M14 -> 7837.1525 | N15: =N13*N14 -> 4265.6066
A17: RATIOS:
A18: Dividend Payout | B18: =IF('Data Sheet'!B30>0, 'Data Sheet'!B31/'Data Sheet'!B30, 0) -> 0.47819793 | C18: =IF('Data Sheet'!C30>0, 'Data Sheet'!C31/'Data Sheet'!C30, 0) -> 0.39188524 | D18: =IF('Data Sheet'!D30>0, 'Data Sheet'!D31/'Data Sheet'!D30, 0) -> 0.3901321 | E18: =IF('Data Sheet'!E30>0, 'Data Sheet'!E31/'Data Sheet'!E30, 0) -> 0.41152893 | F18: =IF('Data Sheet'!F30>0, 'Data Sheet'!F31/'Data Sheet'!F30, 0) -> 0.35234525 | G18: =IF('Data Sheet'!G30>0, 'Data Sheet'!G31/'Data Sheet'!G30, 0) -> 0.66625095 | H18: =IF('Data Sheet'!H30>0, 'Data Sheet'!H31/'Data Sheet'!H30, 0) -> 0.83408757 | I18: =IF('Data Sheet'!I30>0, 'Data Sheet'!I31/'Data Sheet'!I30, 0) -> 0.65703299 | ... K18: =IF('Data Sheet'!K30>0, 'Data Sheet'!K31/'Data Sheet'!K30, 0) -> 0.28974708
A19: OPM | B19: =IF(B6>0,B6/B4,0) -> 0.19116999 | C19: =IF(C6>0,C6/C4,0) -> 0.21232461 | D19: =IF(D6>0,D6/D4,0) -> 0.203571 | E19: =IF(E6>0,E6/E4,0) -> 0.19221791 | F19: =IF(F6>0,F6/F4,0) -> 0.17122285 | G19: =IF(G6>0,G6/G4,0) -> 0.17077442 | H19: =IF(H6>0,H6/H4,0) -> 0.17799523 | I19: =IF(I6>0,I6/I4,0) -> 0.15866182 | ... L19: =IF(L6>0,L6/L4,0) -> 0.18994301
G22: TRENDS: | H22: 10 YEARS | I22: 7 YEARS | J22: 5 YEARS | K22: 3 YEARS | L22: RECENT | M22: BEST | N22: WORST
G23: Sales Growth | H23: =IF(B4=0,"",POWER($K4/B4,1/9)-1) -> 0.084647666 | I23: =IF(D4=0,"",POWER($K4/D4,1/7)-1) -> 0.10895838 | J23: =IF(F4=0,"",POWER($K4/F4,1/5)-1) -> 0.081280756 | K23: =IF(H4=0,"",POWER($K4/H4, 1/3)-1) -> 0.17384915 | L23: =IF(ISERROR(MAX(IF(J4=0,"",(K4-J4)/J4),IF(K4=0,"",(L4-K4)/K4))),"",MAX(IF(J4=0,"",(K4-J4)/J4),IF(K4=0,"",(L4-K4)/K4))) -> 0.2308315 | M23: =MAX(K23:L23) -> 0.2308315 | N23: =MIN(H23:L23) -> 0.081280756
G24: OPM | H24: =IF(SUM(B4:$K$4)=0,"",SUMPRODUCT(B19:$K$19,B4:$K$4)/SUM(B4:$K$4)) -> 0.18366813 | I24: =IF(SUM(E4:$K$4)=0,"",SUMPRODUCT(E19:$K$19,E4:$K$4)/SUM(E4:$K$4)) -> 0.1782141 | J24: =IF(SUM(G4:$K$4)=0,"",SUMPRODUCT(G19:$K$19,G4:$K$4)/SUM(G4:$K$4)) -> 0.17739613 | K24: =IF(SUM(I4:$K$4)=0, "", SUMPRODUCT(I19:$K$19,I4:$K$4)/SUM(I4:$K$4)) -> 0.17898163 | L24: =L19 -> 0.18994301 | M24: =MAX(K24:L24) -> 0.18994301 | N24: =MIN(H24:L24) -> 0.17739613
G25: Price to Earning | H25: =IF(ISERROR(AVERAGEIF(B14:$L14,">0")),"",AVERAGEIF(B14:$L14,">0")) -> 20.395644 | I25: =IF(ISERROR(AVERAGEIF(E14:$L14,">0")),"",AVERAGEIF(E14:$L14,">0")) -> 21.002114 | J25: =IF(ISERROR(AVERAGEIF(G14:$L14,">0")),"",AVERAGEIF(G14:$L14,">0")) -> 22.015432 | K25: =IF(ISERROR(AVERAGEIF(I14:$L14,">0")),"",AVERAGEIF(I14:$L14,">0")) -> 24.748076 | L25: =L14 -> 30.570137 | M25: =MAX(K25:L25) -> 30.570137 | N25: =MIN(H25:L25) -> 20.395644

Sheet Quarters
A1: ='Profit & Loss'!A1 -> BAJAJ AUTO LTD | E1: =UPDATE
A3: Narration | B3: ='Data Sheet'!B41 -> 44834 | C3: ='Data Sheet'!C41 -> 44926 | D3: ='Data Sheet'!D41 -> 45016 | E3: ='Data Sheet'!E41 -> 45107 | F3: ='Data Sheet'!F41 -> 45199 | G3: ='Data Sheet'!G41 -> 45291 | H3: ='Data Sheet'!H41 -> 45382 | I3: ='Data Sheet'!I41 -> 45473 | ... K3: ='Data Sheet'!K41 -> 45657
A4: Sales | B4: ='Data Sheet'!B42 -> 10202.71 | C4: ='Data Sheet'!C42 -> 9318.54 | D4: ='Data Sheet'!D42 -> 8929.23 | E4: ='Data Sheet'!E42 -> 10311.91 | F4: ='Data Sheet'!F42 -> 10838.24 | G4: ='Data Sheet'!G42 -> 12165.33 | H4: ='Data Sheet'!H42 -> 11554.95 | I4: ='Data Sheet'!I42 -> 11932.07 | ... K4: ='Data Sheet'!K42 -> 13168.88
A5: Expenses | B5: ='Data Sheet'!B43 -> 8453.07 | C5: ='Data Sheet'!C43 -> 7561.25 | D5: ='Data Sheet'!D43 -> 7272.02 | E5: ='Data Sheet'!E43 -> 8379.64 | F5: ='Data Sheet'!F43 -> 8708.11 | G5: ='Data Sheet'!G43 -> 9750.43 | H5: ='Data Sheet'!H43 -> 9270.69 | I5: ='Data Sheet'!I43 -> 9561.63 | ... K5: ='Data Sheet'!K43 -> 10418.05
A6: Operating Profit | B6: ='Data Sheet'!B50 -> 1749.64 | C6: ='Data Sheet'!C50 -> 1757.29 | D6: ='Data Sheet'!D50 -> 1657.21 | E6: ='Data Sheet'!E50 -> 1932.27 | F6: ='Data Sheet'!F50 -> 2130.13 | G6: ='Data Sheet'!G50 -> 2414.9 | H6: ='Data Sheet'!H50 -> 2284.26 | I6: ='Data Sheet'!I50 -> 2370.44 | ... K6: ='Data Sheet'!K50 -> 2750.83
A7: Other Income | B7: ='Data Sheet'!B44 -> 531.98 | C7: ='Data Sheet'!C44 -> 270.53 | D7: ='Data Sheet'!D44 -> 594.66 | E7: ='Data Sheet'!E44 -> 351.1 | F7: ='Data Sheet'!F44 -> 552.25 | G7: ='Data Sheet'!G44 -> 356.33 | H7: ='Data Sheet'!H44 -> 443.93 | I7: ='Data Sheet'!I44 -> 335.32 | ... K7: ='Data Sheet'!K44 -> 347.53
A8: Depreciation | B8: ='Data Sheet'!B45 -> 67.48 | C8: ='Data Sheet'!C45 -> 74.82 | D8: ='Data Sheet'!D45 -> 75.99 | E8: ='Data Sheet'!E45 -> 87.23 | F8: ='Data Sheet'!F45 -> 91.82 | G8: ='Data Sheet'!G45 -> 92.91 | H8: ='Data Sheet'!H45 -> 92.81 | I8: ='Data Sheet'!I45 -> 95.01 | ... K8: ='Data Sheet'!K45 -> 101.72
A9: Interest | B9: ='Data Sheet'!B46 -> 10.92 | C9: ='Data Sheet'!C46 -> 8.48 | D9: ='Data Sheet'!D46 -> 15.77 | E9: ='Data Sheet'!E46 -> 12.09 | F9: ='Data Sheet'!F46 -> 6.54 | G9: ='Data Sheet'!G46 -> 12.1 | H9: ='Data Sheet'!H46 -> 29.63 | I9: ='Data Sheet'!I46 -> 46.97 | ... K9: ='Data Sheet'!K46 -> 120.21
A10: Profit before tax | B10: ='Data Sheet'!B47 -> 2203.22 | C10: ='Data Sheet'!C47 -> 1944.52 | D10: ='Data Sheet'!D47 -> 2160.11 | E10: ='Data Sheet'!E47 -> 2184.05 | F10: ='Data Sheet'!F47 -> 2584.02 | G10: ='Data Sheet'!G47 -> 2666.22 | H10: ='Data Sheet'!H47 -> 2605.75 | I10: ='Data Sheet'!I47 -> 2563.78 | ... K10: ='Data Sheet'!K47 -> 2876.43
A11: Tax | B11: ='Data Sheet'!B48 -> 483.78 | C11: ='Data Sheet'!C48 -> 471.82 | D11: ='Data Sheet'!D48 -> 455.37 | E11: ='Data Sheet'!E48 -> 539.91 | F11: ='Data Sheet'!F48 -> 563.97 | G11: ='Data Sheet'!G48 -> 633.6 | H11: ='Data Sheet'!H48 -> 594.32 | I11: ='Data Sheet'!I48 -> 621.99 | ... K11: ='Data Sheet'!K48 -> 680.78
A12: Net profit | B12: ='Data Sheet'!B49 -> 1719.44 | C12: ='Data Sheet'!C49 -> 1472.7 | D12: ='Data Sheet'!D49 -> 1704.74 | E12: ='Data Sheet'!E49 -> 1644.14 | F12: ='Data Sheet'!F49 -> 2020.05 | G12: ='Data Sheet'!G49 -> 2032.62 | H12: ='Data Sheet'!H49 -> 2011.43 | I12: ='Data Sheet'!I49 -> 1941.79 | ... K12: ='Data Sheet'!K49 -> 2195.65
A14: OPM | B14: =IF(B4>0,B6/B4,"") -> 0.17148777 | C14: =IF(C4>0,C6/C4,"") -> 0.18857997 | D14: =IF(D4>0,D6/D4,"") -> 0.18559383 | E14: =IF(E4>0,E6/E4,"") -> 0.18738236 | F14: =IF(F4>0,F6/F4,"") -> 0.19653837 | G14: =IF(G4>0,G6/G4,"") -> 0.19850674 | H14: =IF(H4>0,H6/H4,"") -> 0.19768671 | I14: =IF(I4>0,I6/I4,"") -> 0.19866125 | ... K14: =IF(K4>0,K6/K4,"") -> 0.20888868

Sheet Balance Sheet
A1: ='Profit & Loss'!A1 -> BAJAJ AUTO LTD | E1: =UPDATE
A3: Narration | B3: ='Data Sheet'!B56 -> 42094 | C3: ='Data Sheet'!C56 -> 42460 | D3: ='Data Sheet'!D56 -> 42825 | E3: ='Data Sheet'!E56 -> 43190 | F3: ='Data Sheet'!F56 -> 43555 | G3: ='Data Sheet'!G56 -> 43921 | H3: ='Data Sheet'!H56 -> 44286 | I3: ='Data Sheet'!I56 -> 44651 | ... K3: ='Data Sheet'!K56 -> 45382
A4: Equity Share Capital | B4: ='Data Sheet'!B57 -> 289.37 | C4: ='Data Sheet'!C57 -> 289.37 | D4: ='Data Sheet'!D57 -> 289.37 | E4: ='Data Sheet'!E57 -> 289.37 | F4: ='Data Sheet'!F57 -> 289.37 | G4: ='Data Sheet'!G57 -> 289.37 | H4: ='Data Sheet'!H57 -> 289.37 | I4: ='Data Sheet'!I57 -> 289.37 | ... K4: ='Data Sheet'!K57 -> 279.18
A5: Reserves | B5: ='Data Sheet'!B58 -> 10805.95 | C5: ='Data Sheet'!C58 -> 13730.94 | D5: ='Data Sheet'!D58 -> 17567.2 | E5: ='Data Sheet'!E58 -> 20135.87 | F5: ='Data Sheet'!F58 -> 22944.44 | G5: ='Data Sheet'!G58 -> 21372.71 | H5: ='Data Sheet'!H58 -> 26984.06 | I5: ='Data Sheet'!I58 -> 29570.28 | ... K5: ='Data Sheet'!K58 -> 28683.23
A6: Borrowings | B6: ='Data Sheet'!B59 -> 112.35 | C6: ='Data Sheet'!C59 -> 117.86 | D6: ='Data Sheet'!D59 -> 119.9 | E6: ='Data Sheet'!E59 -> 120.77 | F6: ='Data Sheet'!F59 -> 124.52 | G6: ='Data Sheet'!G59 -> 125.59 | H6: ='Data Sheet'!H59 -> 121.46 | I6: ='Data Sheet'!I59 -> 122.77 | ... K6: ='Data Sheet'!K59 -> 1911.74
A7: Other Liabilities | B7: ='Data Sheet'!B60 -> 4757.93 | C7: ='Data Sheet'!C60 -> 3102.2 | D7: ='Data Sheet'!D60 -> 3661.15 | E7: ='Data Sheet'!E60 -> 4594.99 | F7: ='Data Sheet'!F60 -> 5476.08 | G7: ='Data Sheet'!G60 -> 4722.35 | H7: ='Data Sheet'!H60 -> 6206.82 | I7: ='Data Sheet'!I60 -> 5128.79 | ... K7: ='Data Sheet'!K60 -> 8469.54
A8: Total | B8: ='Data Sheet'!B61 -> 15965.6 | C8: ='Data Sheet'!C61 -> 17240.37 | D8: ='Data Sheet'!D61 -> 21637.62 | E8: ='Data Sheet'!E61 -> 25141 | F8: ='Data Sheet'!F61 -> 28834.41 | G8: ='Data Sheet'!G61 -> 26510.02 | H8: ='Data Sheet'!H61 -> 33601.71 | I8: ='Data Sheet'!I61 -> 35111.21 | ... K8: ='Data Sheet'!K61 -> 39343.69
A10: Net Block | B10: ='Data Sheet'!B62 -> 2448.03 | C10: ='Data Sheet'!C62 -> 2025.67 | D10: ='Data Sheet'!D62 -> 2001.79 | E10: ='Data Sheet'!E62 -> 1878.33 | F10: ='Data Sheet'!F62 -> 1763.94 | G10: ='Data Sheet'!G62 -> 1699.02 | H10: ='Data Sheet'!H62 -> 1667.55 | I10: ='Data Sheet'!I62 -> 1836.05 | ... K10: ='Data Sheet'!K62 -> 3217.37
A11: Capital Work in Progress | B11: ='Data Sheet'!B63 -> 254.94 | C11: ='Data Sheet'!C63 -> 52.24 | D11: ='Data Sheet'!D63 -> 42.17 | E11: ='Data Sheet'!E63 -> 56.47 | F11: ='Data Sheet'!F63 -> 48.02 | G11: ='Data Sheet'!G63 -> 60.19 | H11: ='Data Sheet'!H63 -> 15.98 | I11: ='Data Sheet'!I63 -> 77.21 | ... K11: ='Data Sheet'!K63 -> 35.1
A12: Investments | B12: ='Data Sheet'!B64 -> 8985.25 | C12: ='Data Sheet'!C64 -> 11067.23 | D12: ='Data Sheet'!D64 -> 15477.04 | E12: ='Data Sheet'!E64 -> 18894.57 | F12: ='Data Sheet'!F64 -> 20602.85 | G12: ='Data Sheet'!G64 -> 19913.58 | H12: ='Data Sheet'!H64 -> 24686.65 | I12: ='Data Sheet'!I64 -> 26634.12 | ... K12: ='Data Sheet'!K64 -> 28086.68
A13: Other Assets | B13: ='Data Sheet'!B65 -> 4277.38 | C13: ='Data Sheet'!C65 -> 4095.23 | D13: ='Data Sheet'!D65 -> 4116.62 | E13: ='Data Sheet'!E65 -> 4311.63 | F13: ='Data Sheet'!F65 -> 6419.6 | G13: ='Data Sheet'!G65 -> 4837.23 | H13: ='Data Sheet'!H65 -> 7231.53 | I13: ='Data Sheet'!I65 -> 6563.83 | ... K13: ='Data Sheet'!K65 -> 8004.54
A14: Total | B14: ='Data Sheet'!B66 -> 15965.6 | C14: ='Data Sheet'!C66 -> 17240.37 | D14: ='Data Sheet'!D66 -> 21637.62 | E14: ='Data Sheet'!E66 -> 25141 | F14: ='Data Sheet'!F66 -> 28834.41 | G14: ='Data Sheet'!G66 -> 26510.02 | H14: ='Data Sheet'!H66 -> 33601.71 | I14: ='Data Sheet'!I66 -> 35111.21 | ... K14: ='Data Sheet'!K66 -> 39343.69
A16: Working Capital | B16: =B13-B7 -> -480.55 | C16: =C13-C7 -> 993.03 | D16: =D13-D7 -> 455.47 | E16: =E13-E7 -> -283.36 | F16: =F13-F7 -> 943.52 | G16: =G13-G7 -> 114.88 | H16: =H13-H7 -> 1024.71 | I16: =I13-I7 -> 1435.04 | ... K16: =K13-K7 -> -465
A17: Debtors | B17: ='Data Sheet'!B67 -> 716.96 | C17: ='Data Sheet'!C67 -> 717.93 | D17: ='Data Sheet'!D67 -> 953.29 | E17: ='Data Sheet'!E67 -> 1491.87 | F17: ='Data Sheet'!F67 -> 2559.69 | G17: ='Data Sheet'!G67 -> 1725.1 | H17: ='Data Sheet'!H67 -> 2716.85 | I17: ='Data Sheet'!I67 -> 1516.38 | ... K17: ='Data Sheet'!K67 -> 2075.53
A18: Inventory | B18: ='Data Sheet'!B68 -> 814.15 | C18: ='Data Sheet'!C68 -> 719.07 | D18: ='Data Sheet'!D68 -> 728.38 | E18: ='Data Sheet'!E68 -> 742.58 | F18: ='Data Sheet'!F68 -> 961.51 | G18: ='Data Sheet'!G68 -> 1063.5 | H18: ='Data Sheet'!H68 -> 1493.89 | I18: ='Data Sheet'!I68 -> 1230.51 | ... K18: ='Data Sheet'!K68 -> 1688.75
A20: Debtor Days | B20: =IF('Profit & Loss'!B4>0,'Balance Sheet'!B17/('Profit & Loss'!B4/365),0) -> 12.117855 | C20: =IF('Profit & Loss'!C4>0,'Balance Sheet'!C17/('Profit & Loss'!C4/365),0) -> 11.608401 | D20: =IF('Profit & Loss'!D4>0,'Balance Sheet'!D17/('Profit & Loss'!D4/365),0) -> 15.994269 | E20: =IF('Profit & Loss'!E4>0,'Balance Sheet'!E17/('Profit & Loss'!E4/365),0) -> 21.599923 | F20: =IF('Profit & Loss'!F4>0,'Balance Sheet'!F17/('Profit & Loss'!F4/365),0) -> 30.776014 | G20: =IF('Profit & Loss'!G4>0,'Balance Sheet'!G17/('Profit & Loss'!G4/365),0) -> 21.045786 | H20: =IF('Profit & Loss'!H4>0,'Balance Sheet'!H17/('Profit & Loss'!H4/365),0) -> 35.746635 | I20: =IF('Profit & Loss'!I4>0,'Balance Sheet'!I17/('Profit & Loss'!I4/365),0) -> 16.698855 | ... K20: =IF('Profit & Loss'!K4>0,'Balance Sheet'!K17/('Profit & Loss'!K4/365),0) -> 16.883468
A21: Inventory Turnover | B21: =IF('Balance Sheet'!B18>0,'Profit & Loss'!B4/'Balance Sheet'!B18,0) -> 26.525137 | C21: =IF('Balance Sheet'!C18>0,'Profit & Loss'!C4/'Balance Sheet'!C18,0) -> 31.392896 | D21: =IF('Balance Sheet'!D18>0,'Profit & Loss'!D4/'Balance Sheet'!D18,0) -> 29.867267 | E21: =IF('Balance Sheet'!E18>0,'Profit & Loss'!E4/'Balance Sheet'!E18,0) -> 33.94911 | F21: =IF('Balance Sheet'!F18>0,'Profit & Loss'!F4/'Balance Sheet'!F18,0) -> 31.57287 | G21: =IF('Balance Sheet'!G18>0,'Profit & Loss'!G4/'Balance Sheet'!G18,0) -> 28.132252 | H21: =IF('Balance Sheet'!H18>0,'Profit & Loss'!H4/'Balance Sheet'!H18,0) -> 18.569694 | I21: =IF('Balance Sheet'!I18>0,'Profit & Loss'!I4/'Balance Sheet'!I18,0) -> 26.93575 | ... K21: =IF('Balance Sheet'!K18>0,'Profit & Loss'!K4/'Balance Sheet'!K18,0) -> 26.570203
A23: Return on Equity | B23: =IF(SUM('Balance Sheet'!B4:B5)>0,'Profit & Loss'!B12/SUM('Balance Sheet'!B4:B5),"") -> 0.27269425 | C23: =IF(SUM('Balance Sheet'!C4:C5)>0,'Profit & Loss'!C12/SUM('Balance Sheet'!C4:C5),"") -> 0.28966835 | D23: =IF(SUM('Balance Sheet'!D4:D5)>0,'Profit & Loss'!D12/SUM('Balance Sheet'!D4:D5),"") -> 0.22845877 | E23: =IF(SUM('Balance Sheet'!E4:E5)>0,'Profit & Loss'!E12/SUM('Balance Sheet'!E4:E5),"") -> 0.20655571 | F23: =IF(SUM('Balance Sheet'!F4:F5)>0,'Profit & Loss'!F12/SUM('Balance Sheet'!F4:F5),"") -> 0.2120879 | G23: =IF(SUM('Balance Sheet'!G4:G5)>0,'Profit & Loss'!G12/SUM('Balance Sheet'!G4:G5),"") -> 0.24060063 | H23: =IF(SUM('Balance Sheet'!H4:H5)>0,'Profit & Loss'!H12/SUM('Balance Sheet'!H4:H5),"") -> 0.17808614 | I23: =IF(SUM('Balance Sheet'!I4:I5)>0,'Profit & Loss'!I12/SUM('Balance Sheet'!I4:I5),"") -> 0.20649505 | ... K23: =IF(SUM('Balance Sheet'!K4:K5)>0,'Profit & Loss'!K12/SUM('Balance Sheet'!K4:K5),"") -> 0.26614636
A24: Return on Capital Emp | C24: =IF((B4+B5+B6+C4+C5+C6)>0,('Profit & Loss'!C10+'Profit & Loss'!C9)*2/(B4+B5+B6+C4+C5+C6),"") -> 0.44819505 | D24: =IF((C4+C5+C6+D4+D5+D6)>0,('Profit & Loss'!D10+'Profit & Loss'!D9)*2/(C4+C5+C6+D4+D5+D6),"") -> 0.34806244 | E24: =IF((D4+D5+D6+E4+E5+E6)>0,('Profit & Loss'!E10+'Profit & Loss'!E9)*2/(D4+D5+D6+E4+E5+E6),"") -> 0.30811723 | F24: =IF((E4+E5+E6+F4+F5+F6)>0,('Profit & Loss'!F10+'Profit & Loss'!F9)*2/(E4+E5+E6+F4+F5+F6),"") -> 0.31705567 | G24: =IF((F4+F5+F6+G4+G5+G6)>0,('Profit & Loss'!G10+'Profit & Loss'!G9)*2/(F4+F5+F6+G4+G5+G6),"") -> 0.29660612 | H24: =IF((G4+G5+G6+H4+H5+H6)>0,('Profit & Loss'!H10+'Profit & Loss'!H9)*2/(G4+G5+G6+H4+H5+H6),"") -> 0.25407746 | I24: =IF((H4+H5+H6+I4+I5+I6)>0,('Profit & Loss'!I10+'Profit & Loss'!I9)*2/(H4+H5+H6+I4+I5+I6),"") -> 0.26701635 | J24: =IF((I4+I5+I6+J4+J5+J6)>0,('Profit & Loss'!J10+'Profit & Loss'!J9)*2/(I4+I5+I6+J4+J5+J6),"") -> 0.26506574 | K24: =IF((J4+J5+J6+K4+K5+K6)>0,('Profit & Loss'!K10+'Profit & Loss'!K9)*2/(J4+J5+J6+K4+K5+K6),"") -> 0.33467241
C26: =C16-B16 -> 1473.58 | D26: =D16-C16 -> -537.56 | E26: =E16-D16 -> -738.83 | F26: =F16-E16 -> 1226.88 | G26: =G16-F16 -> -828.64 | H26: =H16-G16 -> 909.83 | I26: =I16-H16 -> 410.33 | J26: =J16-I16 -> -1059.69 | K26: =K16-J16 -> -840.35

Sheet Cash Flow
A1: ='Balance Sheet'!A1 -> BAJAJ AUTO LTD | E1: =UPDATE
A3: Narration | B3: ='Data Sheet'!B81 -> 42094 | C3: ='Data Sheet'!C81 -> 42460 | D3: ='Data Sheet'!D81 -> 42825 | E3: ='Data Sheet'!E81 -> 43190 | F3: ='Data Sheet'!F81 -> 43555 | G3: ='Data Sheet'!G81 -> 43921 | H3: ='Data Sheet'!H81 -> 44286 | I3: ='Data Sheet'!I81 -> 44651 | ... K3: ='Data Sheet'!K81 -> 45382
A4: Cash from Operating Activity | B4: ='Data Sheet'!B82 -> 2113.8 | C4: ='Data Sheet'!C82 -> 3689.85 | D4: ='Data Sheet'!D82 -> 3267.36 | E4: ='Data Sheet'!E82 -> 4327.84 | F4: ='Data Sheet'!F82 -> 2486.86 | G4: ='Data Sheet'!G82 -> 3850.44 | H4: ='Data Sheet'!H82 -> 3119.88 | I4: ='Data Sheet'!I82 -> 4197.21 | ... K4: ='Data Sheet'!K82 -> 6558.16
A5: Cash from Investing Activity | B5: ='Data Sheet'!B83 -> -379.66 | C5: ='Data Sheet'!C83 -> -67.52 | D5: ='Data Sheet'!D83 -> -3609.68 | E5: ='Data Sheet'!E83 -> -1954.48 | F5: ='Data Sheet'!F83 -> -272.77 | G5: ='Data Sheet'!G83 -> 1765.83 | H5: ='Data Sheet'!H83 -> -2869.15 | I5: ='Data Sheet'!I83 -> 276.2 | ... K5: ='Data Sheet'!K83 -> -71.97
A6: Cash from Financing Activity | B6: ='Data Sheet'!B84 -> -1644.18 | C6: ='Data Sheet'!C84 -> -3384.08 | D6: ='Data Sheet'!D84 -> -190.09 | E6: ='Data Sheet'!E84 -> -1885.26 | F6: ='Data Sheet'!F84 -> -2074.05 | G6: ='Data Sheet'!G84 -> -6246.51 | H6: ='Data Sheet'!H84 -> -19.52 | I6: ='Data Sheet'!I84 -> -4056.33 | ... K6: ='Data Sheet'!K84 -> -6167.36
A7: Net Cash Flow | B7: ='Data Sheet'!B85 -> 89.96 | C7: ='Data Sheet'!C85 -> 238.25 | D7: ='Data Sheet'!D85 -> -532.41 | E7: ='Data Sheet'!E85 -> 488.1 | F7: ='Data Sheet'!F85 -> 140.04 | G7: ='Data Sheet'!G85 -> -630.24 | H7: ='Data Sheet'!H85 -> 231.21 | I7: ='Data Sheet'!I85 -> 417.08 | ... K7: ='Data Sheet'!K85 -> 318.83

Sheet Data Sheet
A1: COMPANY NAME | B1: BAJAJ AUTO LTD | E1: =IF(B2<>B3, "A NEW VERSION OF THE WORKSHEET IS AVAILABLE", "")
A6: Number of shares | B6: =IF(B9>0, B9/B8, 0) -> 27.926631
A7: Face Value | B7: 10
A8: Current Price | B8: 8247.5
A9: Market Capitalization | B9: 230324.89
A15: PROFIT & LOSS
A16: Report Date | B16: 42094 | C16: 42460 | D16: 42825 | E16: 43190 | F16: 43555 | G16: 43921 | H16: 44286 | I16: 44651 | J16: 45016 | K16: 45382
A17: Sales | B17: 21595.44 | C17: 22573.69 | D17: 21754.72 | E17: 25209.93 | F17: 30357.63 | G17: 29918.65 | H17: 27741.08 | I17: 33144.71 | J17: 36455.38 | K17: 44870.43
A18: Raw Material Cost | B18: 14907.89 | C18: 14993.41 | D18: 14667.83 | E18: 17400.41 | F18: 21854.1 | G18: 21071.29 | H18: 19829.13 | I18: 24141.86 | J18: 26221.58 | K18: 31969.57
A19: Change in Inventory | B19: 56.46 | C19: -63.45 | D19: 43.68 | E19: -9.68 | F19: 56.42 | G19: 63.01 | H19: 219.48 | I19: -187.96 | J19: 100.33 | K19: 76.34
A20: Power and Fuel | B20: 114.8 | C20: 120.66 | D20: 96.46 | E20: 100.26 | F20: 115.01 | G20: 116.57 | H20: 91.34 | I20: 108.01 | J20: 122.6 | K20: 147.94
A21: Other Mfr. Exp | B21: 655.78 | C21: 644.19 | D21: 547.54 | E21: 550.16 | F21: 633.99 | G21: 698.83 | H21: 597.11 | I21: 836.28 | J21: 743.55 | K21: 734.43
A22: Employee Cost | B22: 901.3 | C22: 920.01 | D22: 999.83 | E22: 1072.59 | F22: 1260.32 | G22: 1395 | H22: 1296.07 | I22: 1366 | J22: 1488.1 | K22: 1631.06
A23: Selling and admin | B23: 707.58 | C23: 795.66 | D23: 699.73 | E23: 852.82 | F23: 940.92 | G23: 1020.98 | H23: 654.86 | I23: 644.9 | J23: 852.61 | K23: 999.37
A24: Other Expenses | B24: 236.15 | C24: 243.36 | D24: 358.38 | E24: 378.21 | F24: 411.79 | G24: 569.65 | H24: 554.27 | I24: 600.9 | J24: 662.63 | K24: 699.72
A25: Other Income | B25: 228.5 | C25: 1194.15 | D25: 1467.61 | E25: 1403.72 | F25: 2027.83 | G25: 1832.38 | H25: 1569.68 | I25: 2671.3 | J25: 1702.7 | K25: 1700.49
A26: Depreciation | B26: 267.46 | C26: 307.16 | D26: 307.29 | E26: 314.8 | F26: 265.69 | G26: 246.43 | H26: 259.37 | I26: 269.76 | J26: 285.85 | K26: 364.77 | L26: =AVERAGE(E26:K26) -> 286.66714
A27: Interest | B27: 6.49 | C27: 1.05 | D27: 1.4 | E27: 1.31 | F27: 4.48 | G27: 3.16 | H27: 6.66 | I27: 8.66 | J27: 39.51 | K27: 60.36
A28: Profit before tax | B28: 4082.95 | C28: 5678.89 | D28: 5587.55 | E28: 5933.41 | F28: 6955.58 | G28: 6692.13 | H28: 6241.43 | I28: 7651.68 | J28: 7841.98 | K28: 10040.04
A29: Tax | B29: 1271.05 | C29: 1617.65 | D29: 1508.07 | E29: 1714.47 | F29: 2027.98 | G29: 1480.22 | H29: 1384.41 | I29: 1485.81 | J29: 1781.77 | K29: 2331.8
A30: Net profit | B30: 3025.63 | C30: 4061.24 | D30: 4079.49 | E30: 4218.95 | F30: 4927.61 | G30: 5211.91 | H30: 4857.02 | I30: 6165.87 | J30: 6060.21 | K30: 7708.24
A31: Dividend Amount | B31: 1446.85 | C31: 1591.54 | D31: 1591.54 | E31: 1736.22 | F31: 1736.22 | G31: 3472.44 | H31: 4051.18 | I31: 4051.18 | J31: 3961.44 | K31: 2233.44
I33: =SUM(I18:I22) -> 26264.19 | J33: =SUM(J18:J22) -> 28676.16 | K33: =SUM(K18:K22) -> 34559.34
G34: =SUM(G23:G24) -> 1590.63 | H34: =SUM(H23:H24) -> 1209.13 | I34: =SUM(I23:I24) -> 1245.8 | J34: =SUM(J23:J24) -> 1515.24 | K34: =SUM(K23:K24) -> 1699.09
A40: Quarters
A41: Report Date | B41: 44834 | C41: 44926 | D41: 45016 | E41: 45107 | F41: 45199 | G41: 45291 | H41: 45382 | I41: 45473 | J41: 45565 | K41: 45657
A42: Sales | B42: 10202.71 | C42: 9318.54 | D42: 8929.23 | E42: 10311.91 | F42: 10838.24 | G42: 12165.33 | H42: 11554.95 | I42: 11932.07 | J42: 13247.28 | K42: 13168.88
A43: Expenses | B43: 8453.07 | C43: 7561.25 | D43: 7272.02 | E43: 8379.64 | F43: 8708.11 | G43: 9750.43 | H43: 9270.69 | I43: 9561.63 | J43: 11174.05 | K43: 10418.05
A44: Other Income | B44: 531.98 | C44: 270.53 | D44: 594.66 | E44: 351.1 | F44: 552.25 | G44: 356.33 | H44: 443.93 | I44: 335.32 | J44: 399.33 | K44: 347.53
A45: Depreciation | B45: 67.48 | C45: 74.82 | D45: 75.99 | E45: 87.23 | F45: 91.82 | G45: 92.91 | H45: 92.81 | I45: 95.01 | J45: 98.27 | K45: 101.72
A46: Interest | B46: 10.92 | C46: 8.48 | D46: 15.77 | E46: 12.09 | F46: 6.54 | G46: 12.1 | H46: 29.63 | I46: 46.97 | J46: 75.2 | K46: 120.21
A47: Profit before tax | B47: 2203.22 | C47: 1944.52 | D47: 2160.11 | E47: 2184.05 | F47: 2584.02 | G47: 2666.22 | H47: 2605.75 | I47: 2563.78 | J47: 2299.09 | K47: 2876.43
A48: Tax | B48: 483.78 | C48: 471.82 | D48: 455.37 | E48: 539.91 | F48: 563.97 | G48: 633.6 | H48: 594.32 | I48: 621.99 | J48: 913.65 | K48: 680.78
A49: Net profit | B49: 1719.44 | C49: 1472.7 | D49: 1704.74 | E49: 1644.14 | F49: 2020.05 | G49: 2032.62 | H49: 2011.43 | I49: 1941.79 | J49: 1385.44 | K49: 2195.65
A50: Operating Profit | B50: 1749.64 | C50: 1757.29 | D50: 1657.21 | E50: 1932.27 | F50: 2130.13 | G50: 2414.9 | H50: 2284.26 | I50: 2370.44 | J50: 2073.23 | K50: 2750.83
A55: BALANCE SHEET
A56: Report Date | B56: 42094 | C56: 42460 | D56: 42825 | E56: 43190 | F56: 43555 | G56: 43921 | H56: 44286 | I56: 44651 | J56: 45016 | K56: 45382
A57: Equity Share Capital | B57: 289.37 | C57: 289.37 | D57: 289.37 | E57: 289.37 | F57: 289.37 | G57: 289.37 | H57: 289.37 | I57: 289.37 | J57: 282.96 | K57: 279.18
A58: Reserves | B58: 10805.95 | C58: 13730.94 | D58: 17567.2 | E58: 20135.87 | F58: 22944.44 | G58: 21372.71 | H58: 26984.06 | I58: 29570.28 | J58: 29078.58 | K58: 28683.23
A59: Borrowings | B59: 112.35 | C59: 117.86 | D59: 119.9 | E59: 120.77 | F59: 124.52 | G59: 125.59 | H59: 121.46 | I59: 122.77 | J59: 124.23 | K59: 1911.74
A60: Other Liabilities | B60: 4757.93 | C60: 3102.2 | D60: 3661.15 | E60: 4594.99 | F60: 5476.08 | G60: 4722.35 | H60: 6206.82 | I60: 5128.79 | J60: 5650.68 | K60: 8469.54
A61: Total | B61: 15965.6 | C61: 17240.37 | D61: 21637.62 | E61: 25141 | F61: 28834.41 | G61: 26510.02 | H61: 33601.71 | I61: 35111.21 | J61: 35136.45 | K61: 39343.69
A62: Net Block | B62: 2448.03 | C62: 2025.67 | D62: 2001.79 | E62: 1878.33 | F62: 1763.94 | G62: 1699.02 | H62: 1667.55 | I62: 1836.05 | J62: 2842.24 | K62: 3217.37
A63: Capital Work in Progress | B63: 254.94 | C63: 52.24 | D63: 42.17 | E63: 56.47 | F63: 48.02 | G63: 60.19 | H63: 15.98 | I63: 77.21 | J63: 85.27 | K63: 35.1
A64: Investments | B64: 8985.25 | C64: 11067.23 | D64: 15477.04 | E64: 18894.57 | F64: 20602.85 | G64: 19913.58 | H64: 24686.65 | I64: 26634.12 | J64: 26182.91 | K64: 28086.68
A65: Other Assets | B65: 4277.38 | C65: 4095.23 | D65: 4116.62 | E65: 4311.63 | F65: 6419.6 | G65: 4837.23 | H65: 7231.53 | I65: 6563.83 | J65: 6026.03 | K65: 8004.54
A66: Total | B66: 15965.6 | C66: 17240.37 | D66: 21637.62 | E66: 25141 | F66: 28834.41 | G66: 26510.02 | H66: 33601.71 | I66: 35111.21 | J66: 35136.45 | K66: 39343.69
A67: Receivables | B67: 716.96 | C67: 717.93 | D67: 953.29 | E67: 1491.87 | F67: 2559.69 | G67: 1725.1 | H67: 2716.85 | I67: 1516.38 | J67: 1752.43 | K67: 2075.53
... A70: No. of Equity Shares | B70: 289367020 | C70: 289367020 | D70: 289367020 | E70: 289367020 | F70: 289367020 | G70: 289367020 | H70: 289367020 | I70: 289367020 | J70: 282957358 | K70: 279179756
A71: New Bonus Shares
A72: Face value | B72: 10 | C72: 10 | D72: 10 | E72: 10 | F72: 10 | G72: 10 | H72: 10 | I72: 10 | J72: 10 | K72: 10
A80: CASH FLOW:
A81: Report Date | B81: 42094 | C81: 42460 | D81: 42825 | E81: 43190 | F81: 43555 | G81: 43921 | H81: 44286 | I81: 44651 | J81: 45016 | K81: 45382
A82: Cash from Operating Activity | B82: 2113.8 | C82: 3689.85 | D82: 3267.36 | E82: 4327.84 | F82: 2486.86 | G82: 3850.44 | H82: 3119.88 | I82: 4197.21 | J82: 5277.42 | K82: 6558.16
A83: Cash from Investing Activity | B83: -379.66 | C83: -67.52 | D83: -3609.68 | E83: -1954.48 | F83: -272.77 | G83: 1765.83 | H83: -2869.15 | I83: 276.2 | J83: 1211.21 | K83: -71.97
A84: Cash from Financing Activity | B84: -1644.18 | C84: -3384.08 | D84: -190.09 | E84: -1885.26 | F84: -2074.05 | G84: -6246.51 | H84: -19.52 | I84: -4056.33 | J84: -7180.7 | K84: -6167.36
A85: Net Cash Flow | B85: 89.96 | C85: 238.25 | D85: -532.41 | E85: 488.1 | F85: 140.04 | G85: -630.24 | H85: 231.21 | I85: 417.08 | J85: -692.07 | K85: 318.83
A90: PRICE: | B90: 2016.6 | C90: 2405.95 | D90: 2805.45 | E90: 2744.7 | F90: 2911.1 | G90: 2022.35 | H90: 3670.6 | I90: 3653 | J90: 3884.75 | K90: 9148.15
A92: DERIVED:
A93: Adjusted Equity Shares in Cr | B93: 28.94 | C93: 28.94 | D93: 28.94 | E93: 28.94 | F93: 28.94 | G93: 28.94 | H93: 28.94 | I93: 28.94 | J93: 28.3 | K93: 27.92

Sheet Valuation
A1: (INR in crores, Financial Year March 31)
A2: Operating Scenario
D3: Historical Period | I3: Forecasted Period
D4: =+E4-1 -> 2022 | E4: 2023 | F4: 2024 | G4: CAGR | H4: 2025 | I4: 2026 | J4: 2027 | K4: 2028 | L4: 2029 | M4: 2030
A5: Sales | D5: ='Profit & Loss'!I4 -> 33144.71 | E5: ='Profit & Loss'!J4 -> 36455.38 | F5: ='Profit & Loss'!K4 -> 44870.43 | H5: =F5*(1+H6) -> 48460.064 | I5: =H5*(1+I6) -> 52336.87 | J5: =I5*(1+J6) -> 56523.819 | K5: =J5*(1+K6) -> 61045.725 | L5: =K5*(1+L6) -> 65929.383 | M5: =L5*(1+M6) -> 71203.733
A6: % growth | E6: =(E5-D5)/D5 -> 0.099885321 | F6: =(F5-E5)/E5 -> 0.2308315 | G6: 0.08 | H6: =G6 -> 0.08 | I6: =H6 -> 0.08 | J6: =I6 -> 0.08 | K6: =J6 -> 0.08 | L6: =K6 -> 0.08 | M6: =L6 -> 0.08
A7: Cost of Goods Sold | C7: 0.8 | D7: ='Data Sheet'!I33 -> 26264.19 | E7: ='Data Sheet'!J33 -> 28676.16 | F7: ='Data Sheet'!K33 -> 34559.34 | H7: =H5*0.8 -> 38768.052 | I7: =I5*0.8 -> 41869.496 | J7: =J5*0.8 -> 45219.055 | K7: =K5*0.8 -> 48836.58 | L7: =L5*0.8 -> 52743.506 | M7: =M5*0.8 -> 56962.987
A8: Gross Profit | D8: =+D5-D7 -> 6880.52 | E8: =+E5-E7 -> 7779.22 | F8: =+F5-F7 -> 10311.09 | H8: =+H5-H7 -> 9692.0129 | I8: =+I5-I7 -> 10467.374 | J8: =+J5-J7 -> 11304.764 | K8: =+K5-K7 -> 12209.145 | L8: =+L5-L7 -> 13185.877 | M8: =+M5-M7 -> 14240.747
A9: % margin | D9: =D8/D5 -> 0.20759029 | E9: =E8/E5 -> 0.21339018 | F9: =F8/F5 -> 0.229797 | H9: =H8/H5 -> 0.2 | I9: =I8/I5 -> 0.2 | J9: =J8/J5 -> 0.2 | K9: =K8/K5 -> 0.2 | L9: =L8/L5 -> 0.2 | M9: =M8/M5 -> 0.2
A10: Selling, General & Administrative | C10: 0.04 | D10: ='Data Sheet'!I34 -> 1245.8 | E10: ='Data Sheet'!J34 -> 1515.24 | F10: ='Data Sheet'!K34 -> 1699.09 | H10: =H5*0.04 -> 1938.4026 | I10: =I5*0.04 -> 2093.4748 | J10: =J5*0.04 -> 2260.9528 | K10: =K5*0.04 -> 2441.829 | L10: =L5*0.04 -> 2637.1753 | M10: =M5*0.04 -> 2848.1493
A11: EBITDA | D11: =D8-D10 -> 5634.72 | E11: =E8-E10 -> 6263.98 | F11: =F8-F10 -> 8612 | H11: =H8-H10 -> 7753.6103 | I11: =I8-I10 -> 8373.8991 | J11: =J8-J10 -> 9043.8111 | K11: =K8-K10 -> 9767.3159 | L11: =L8-L10 -> 10548.701 | M11: =M8-M10 -> 11392.597
A12: % margin | D12: =D11/D5 -> 0.1700036 | E12: =E11/E5 -> 0.17182594 | F12: =F11/F5 -> 0.19193041 | H12: =H11/H5 -> 0.16 | I12: =I11/I5 -> 0.16 | J12: =J11/J5 -> 0.16 | K12: =K11/K5 -> 0.16 | L12: =L11/L5 -> 0.16 | M12: =M11/M5 -> 0.16
A13: Depreciation & Amortization | D13: ='Profit & Loss'!I8 -> 269.76 | E13: ='Profit & Loss'!J8 -> 285.85 | F13: ='Profit & Loss'!K8 -> 364.77 | H13: ='Data Sheet'!L26 -> 286.66714 | I13: =H13 -> 286.66714 | J13: =I13 -> 286.66714 | K13: =J13 -> 286.66714 | L13: =K13 -> 286.66714 | M13: =L13 -> 286.66714
A14: EBIT | D14: =+D11-D13 -> 5364.96 | E14: =+E11-E13 -> 5978.13 | F14: =+F11-F13 -> 8247.23 | H14: =+H11-H13 -> 7466.9432 | I14: =+I11-I13 -> 8087.232 | J14: =+J11-J13 -> 8757.1439 | K14: =+K11-K13 -> 9480.6488 | L14: =+L11-L13 -> 10262.034 | M14: =+M11-M13 -> 11105.93
A15: % margin | D15: =D14/D5 -> 0.16186474 | E15: =E14/E5 -> 0.16398485 | F15: =F14/F5 -> 0.183801 | H15: =H14/H5 -> 0.15408447 | I15: =I14/I5 -> 0.15452265 | J15: =J14/J5 -> 0.15492838 | K15: =K14/K5 -> 0.15530406 | L15: =L14/L5 -> 0.15565191 | M15: =M14/M5 -> 0.15597399
A16: Taxes | C16: 0.26 | D16: =D14*$C$16 -> 1394.8896 | E16: =E14*$C$16 -> 1554.3138 | F16: =F14*$C$16 -> 2144.2798 | H16: =H14*$C$16 -> 1941.4052 | I16: =I14*$C$16 -> 2102.6803 | J16: =J14*$C$16 -> 2276.8574 | K16: =K14*$C$16 -> 2464.9687 | L16: =L14*$C$16 -> 2668.1289 | M16: =M14*$C$16 -> 2887.5418
A17: EBIT(1-T) | D17: =D14*(1-$C$16) -> 3970.0704 | E17: =E14*(1-$C$16) -> 4423.8162 | F17: =F14*(1-$C$16) -> 6102.9502 | H17: =+H14-H16 -> 5525.5379 | I17: =+I14-I16 -> 5984.5517 | J17: =+J14-J16 -> 6480.2865 | K17: =+K14-K16 -> 7015.6801 | L17: =+L14-L16 -> 7593.9052 | M17: =+M14-M16 -> 8218.3883
A19: Plus: Depreciation & Amortization | D19: =D13 -> 269.76 | E19: =E13 -> 285.85 | F19: =F13 -> 364.77 | H19: =H13 -> 286.66714 | I19: =I13 -> 286.66714 | J19: =J13 -> 286.66714 | K19: =K13 -> 286.66714 | L19: =L13 -> 286.66714 | M19: =M13 -> 286.66714
A20: Less: Capital Expenditures | D20: ='Balance Sheet'!I11 -> 77.21 | E20: ='Balance Sheet'!J11 -> 85.27 | F20: ='Balance Sheet'!K11 -> 35.1 | H20: =40 -> 40 | I20: =H20 -> 40 | J20: =H20 -> 40 | K20: =I20 -> 40 | L20: =J20 -> 40 | M20: =K20 -> 40
A21: Less: Inc./(Dec.) in Net Working Capital | D21: ='Balance Sheet'!I26 -> 410.33 | E21: ='Balance Sheet'!J26 -> -1059.69 | F21: ='Balance Sheet'!K26 -> -840.35 | H21: 639.70757 | I21: -1287.177 | J21: -1192.4784 | K21: 385.6034 | L21: -1541.2811 | M21: -1446.5826
A23: Unlevered Free Cash Flow | D23: =+D17+SUM(D19:D21) -> 4727.3704 | E23: =+E17+SUM(E19:E21) -> 3735.2462 | F23: =+F17+SUM(F19:F21) -> 5662.4702 | H23: =+H17+SUM(H19:H21) -> 6491.9126 | I23: =+I17+SUM(I19:I21) -> 5024.0418 | J23: =+J17+SUM(J19:J21) -> 5614.4752 | K23: =+K17+SUM(K19:K21) -> 7727.9507 | L23: =+L17+SUM(L19:L21) -> 6379.2912 | M23: =+M17+SUM(M19:M21) -> 7098.4729
A24: WACC | D24: =C35 -> 0.079916925
A25: Discount Period | H25: 1 | I25: 2 | J25: 3 | K25: 4 | L25: 5 | M25: 6
A26: Discount Factor | H26: =1/((1+$D$24)^(H25)) -> 0.92599715 | I26: =1/((1+$D$24)^(I25)) -> 0.85747073 | J26: =1/((1+$D$24)^(J25)) -> 0.79401546 | K26: =1/((1+$D$24)^(K25)) -> 0.73525605 | L26: =1/((1+$D$24)^(L25)) -> 0.68084501 | M26: =1/((1+$D$24)^(M25)) -> 0.63046055
A27: Present Value of Free Cash Flow | H27: =+H23*H26 -> 6011.4926 | I27: =+I23*I26 -> 4307.9688 | J27: =+J23*J26 -> 4457.9801 | K27: =+K23*K26 -> 5682.0225 | L27: =+L23*L26 -> 4343.3086 | M27: =+M23*M26 -> 4475.3071
C29: WACC Calculation
A31: Risk Free rate of Return -Rf | C31: 0.06 | D31: Beta | F31: 0.63
A32: Risk Premium - Rm-Rf | C32: =11%-C31 -> 0.05 | D32: Cost of debt post tax-Kd | F32: ='Data Sheet'!K27*(1-0.26)/'Data Sheet'!K59 -> 0.023364265
A33: Weight of Debt -Wd | C33: 0.17 | D33: Weight of Equity-We | F33: =1-C33 -> 0.83
A34: Cost of Equity-CAPM | C34: =C31+(F31*C32) -> 0.0915
A35: Cost of Capital-WACC | C35: =(C33*F32)+(F33*C34) -> 0.079916925
A38: Enterprise Value | F38: Equity Value and Share Price | K38: Perpetuity Growth Rate
A39: Total Value Of NPV of Cash flows | D39: =+SUM(H27:M27) -> 29278.08 | F39: Enterprise Value | I39: =+D48 -> 222171.4 | K39: ="Terminal Year Free Cash Flow ("&M4&"E)" -> Terminal Year Free Cash Flow (2030E) | N39: =+M23 -> 7098.4729
F40: Less: Total Debt | I40: ='Balance Sheet'!K6 -> 1911.74 | K40: WACC | N40: =+D24 -> 0.079916925
B41: Terminal Value ( Exit Multiple) | F41: Less: Noncontrolling Interest | I41: 0 | K41: Terminal Value | N41: =+D44 -> 305956.2
A42: ="Terminal Year EBITDA ("&M4&"E)" -> Terminal Year EBITDA (2030E) | D42: =+M11 -> 11392.597 | F42: Plus: Cash and Cash Equivalents | I42: ='Data Sheet'!K69 -> 955.32
A43: Exit Multiple | D43: =N49 -> 26.855703 | K43: Implied Perpetuity Growth Rate | N43: =(N40-(N39/N41))/(1+(N39/N41)) -> 0.055429953
A44: Terminal Value | D44: =+D42*D43 -> 305956.2
A45: Discount Factor | D45: =M26 -> 0.63046055 | F45: Implied Equity Value | I45: =+I39-I40-I41+I42 -> 221214.98 | K45: Implied EV/EBITDA
A46: Present Value of Terminal Value | D46: =+D44*D45 -> 192893.32 | K46: =+F39 -> Enterprise Value | N46: ='Data Sheet'!B9+'Data Sheet'!K59-'Data Sheet'!K69 -> 231281.31
F47: Fully Diluted Shares Outstanding | I47: ='Data Sheet'!B6 -> 27.926631 | K47: 2024 EBITDA | N47: =F11 -> 8612
A48: Enterprise Value with Exit multiple | D48: =D46+D39 -> 222171.4
F49: Implied Share Price | I49: =+IF(ISERROR(I45/I47),"NA",I45/I47) -> 7921.2911 | K49: Implied EV/EBITDA | N49: =+IF(ISERROR(N46/N47),"- x",N46/N47) -> 26.855703
B50: Terminal Value ( Perpetuity Formula)
A51: ="Terminal Year Cash Flow" -> Terminal Year Cash Flow | D51: =+M23 -> 7098.4729 | F51: Share price as on 21-04-2025 | I51: 8248
A52: Perpetuity Growth rate | D52: =N43 -> 0.055429953
A53: Terminal Value | D53: =+IF(ISERROR(D51/(D24-D52)),0,D51/(D24-D52)) -> 289887.74
A54: Discount Factor | D54: =M26 -> 0.63046055
A55: Present Value of Terminal Value | D55: =+D53*D54 -> 182762.78
A57: Enterprise Value with Perpetuity approach | D57: =D55+D39 -> 212040.86
A60: Note:All prices are in crores

Sheet Forecast working capital
A1: Timeline | B1: Values | C1: Forecast | D1: Lower Confidence Bound | E1: Upper Confidence Bound
A2: 42460 | B2: 1473.58
A3: 42825 | B3: -537.56
A4: 43190 | B4: -738.83
A5: 43555 | B5: 1226.88
A6: 43921 | B6: -828.64
A7: 44286 | B7: 909.83
A8: 44651 | B8: 410.33
A9: 45016 | B9: -1059.69
A10: 45382 | B10: -840.35 | C10: -840.35 | D10: -840.35 | E10: -840.35
A11: 45747 | C11: =_xlfn.FORECAST.ETS(A11,$B$2:$B$10,$A$2:$A$10,1,1) -> 639.70757 | D11: =C11-_xlfn.FORECAST.ETS.CONFINT(A11,$B$2:$B$10,$A$2:$A$10,0.95,1,1) -> -620.53077 | E11: =C11+_xlfn.FORECAST.ETS.CONFINT(A11,$B$2:$B$10,$A$2:$A$10,0.95,1,1) -> 1899.9459
A12: 46112 | C12: =_xlfn.FORECAST.ETS(A12,$B$2:$B$10,$A$2:$A$10,1,1) -> -1287.177 | D12: =C12-_xlfn.FORECAST.ETS.CONFINT(A12,$B$2:$B$10,$A$2:$A$10,0.95,1,1) -> -2547.421 | E12: =C12+_xlfn.FORECAST.ETS.CONFINT(A12,$B$2:$B$10,$A$2:$A$10,0.95,1,1) -> -26.932958
A13: 46477 | C13: =_xlfn.FORECAST.ETS(A13,$B$2:$B$10,$A$2:$A$10,1,1) -> -1192.4784 | D13: =C13-_xlfn.FORECAST.ETS.CONFINT(A13,$B$2:$B$10,$A$2:$A$10,0.95,1,1) -> -2452.7325 | E13: =C13+_xlfn.FORECAST.ETS.CONFINT(A13,$B$2:$B$10,$A$2:$A$10,0.95,1,1) -> 67.775667
A14: 46843 | C14: =_xlfn.FORECAST.ETS(A14,$B$2:$B$10,$A$2:$A$10,1,1) -> 385.6034 | D14: =C14-_xlfn.FORECAST.ETS.CONFINT(A14,$B$2:$B$10,$A$2:$A$10,0.95,1,1) -> -885.25496 | E14: =C14+_xlfn.FORECAST.ETS.CONFINT(A14,$B$2:$B$10,$A$2:$A$10,0.95,1,1) -> 1656.4618
A15: 47208 | C15: =_xlfn.FORECAST.ETS(A15,$B$2:$B$10,$A$2:$A$10,1,1) -> -1541.2811 | D15: =C15-_xlfn.FORECAST.ETS.CONFINT(A15,$B$2:$B$10,$A$2:$A$10,0.95,1,1) -> -2812.162 | E15: =C15+_xlfn.FORECAST.ETS.CONFINT(A15,$B$2:$B$10,$A$2:$A$10,0.95,1,1) -> -270.40029
A16: 47573 | C16: =_xlfn.FORECAST.ETS(A16,$B$2:$B$10,$A$2:$A$10,1,1) -> -1446.5826 | D16: =C16-_xlfn.FORECAST.ETS.CONFINT(A16,$B$2:$B$10,$A$2:$A$10,0.95,1,1) -> -2717.4941 | E16: =C16+_xlfn.FORECAST.ETS.CONFINT(A16,$B$2:$B$10,$A$2:$A$10,0.95,1,1) -> -175.67113

Sheet Post merger
A2: EPS ACCRETIVE /DILUTIVE DEAL ANALYSIS WITH DIFFERENT SCENARIOS
A4: EPS Accretive/Dilutive Deal Calculation | K4: EPS Accretive/Dilutive Deal Calculation
A5: INPUT DATA | C5: Scenario 1 | E5: Scenario 2 | G5: Scenario 3 | K5: INPUT DATA | M5: Scenario 1 | N5: Scenario 2 | O5: Scenario 3 | P5: Scenario 4
A6: (figures in INR) | B6: Acquirer | C6: 50% STOCK PAYMENT | E6: 100% STOCK PAYMENT | G6: 0% STOCK PAYMENT | K6: (figures in INR) | L6: Acquirer | M6: Target
B7: & Target | C7: 50% CASH PAYMENT | E7: 0% CASH PAYMENT | G7: 100% CASH PAYMENT | M7: No Premium | O7: Premium offered per Share | P7: 50% cash + 50% stock payment
O8: =O9-M9 -> 52.473717
K9: Share price before announcement of M&A deal | L9: =B10 -> 8248 | M9: =B11 -> 523 | N9: =M9 -> 523 | O9: 575.47372 | P9: =O9 -> 575.47372
A10: Acquirer Share price @ per share | B10: 8248 | C10: =B10 -> 8248 | E10: =C10 -> 8248 | G10: =E10 -> 8248 | K10: Net Operating Income | L10: =L11*L13 -> 6.9492688e+10 | M10: =M11*M13 -> 3.2357443e+09 | N10: =M10 -> 3.2357443e+09 | O10: =M10 -> 3.2357443e+09 | P10: =O10 -> 3.2357443e+09
A11: Target company share price @per share | B11: 523 | C11: =B11 -> 523 | E11: =C11 -> 523 | G11: =E11 -> 523 | K11: Earning per share-EPS | L11: =L9/L12 -> 248.91736 | M11: =M9/M12 -> 11.673172 | N11: =N10/N13 -> 11.673172 | O11: =O10/O13 -> 11.673172 | P11: =P10/P13 -> 11.673172
A12: Premium Offered | B12: 0.10038241 | C12: =B12 -> 0.10038241 | E12: =C12 -> 0.10038241 | G12: =E12 -> 0.10038241 | K12: Price/earning -P/E ratio | L12: ='Profit & Loss'!K14 -> 33.135495 | M12: ='[1]Profit & Loss'!$K$14 -> 44.803589 | N12: =N9/N11 -> 44.803589 | O12: =O9/O11 -> 49.298829 | P12: =P9/P11 -> 49.298829
A13: Offer Value | B13: =B11*(1+B12) -> 575.5 | C13: =C11*(1+C12) -> 575.5 | E13: =C13 -> 575.5 | G13: =E13 -> 575.5 | K13: Number of shares outstanding | L13: =B15 -> 279179756 | M13: =B14 -> 277194946 | N13: =M13 -> 277194946 | O13: =M13 -> 277194946 | P13: =O13 -> 277194946
A14: NO. of Shares outstanding of Target | B14: 277194946 | C14: =B14 -> 277194946 | E14: =C14 -> 277194946 | G14: =E14 -> 277194946 | K14: Increase in Net income due to synergy gains | M14: 0 | N14: 1500000000 | O14: 0 | P14: 0
A15: NO. of Shares outstanding of Acquirer | B15: 279179756 | C15: =B15 -> 279179756 | E15: =C15 -> 279179756 | G15: =E15 -> 279179756
A16: Equity Value for Purchase | B16: =B13*B14 -> 1.5952569e+11 | C16: =C13*C14 -> 1.5952569e+11 | E16: =C16 -> 1.5952569e+11 | G16: =E16 -> 1.5952569e+11 | K16: Scenario-1
A17: Add: Total Debt Of Target Firm | B17: =[1]Valuation!$I$40*10000000 -> 6.746e+08 | C17: =B17 -> 6.746e+08 | E17: =C17 -> 6.746e+08 | G17: =E17 -> 6.746e+08 | K17: Acquirer acquires target firm at Market price and pays through stock
A18: Less: Cash & cash equivalents Of Target Firm | B18: =[1]Valuation!$I$42*10000000 -> 2349500000 | C18: =B18 -> 2349500000 | E18: =C18 -> 2349500000 | G18: =E18 -> 2349500000 | K18: P/E ratio of Target > P/E ratio of Acquirer
A19: Enterprise Value Of Target Firm | B19: =B16+B17-B18 -> 1.5785079e+11 | C19: =C16+C17-C18 -> 1.5785079e+11 | E19: =C19 -> 1.5785079e+11 | G19: =E19 -> 1.5785079e+11 | K19: Exchange ratio more than one
A21: Financing Plan Of acquirer for acquiring Target Firm | L21: Acquirer | M21: Target | N21: Post M&A
A22: Payment through Stock | C22: 0.5 | D22: =C22*B16 -> 7.9762846e+10 | E22: 1 | F22: =E22*B16 -> 1.5952569e+11 | G22: 0 | H22: =G22*B16 -> 0 | K22: Share price before announcement | L22: =L9 -> 8248 | M22: =M9 -> 523
A23: Payment through Cash | C23: =1-C22 -> 0.5 | D23: =C23*B16 -> 7.9762846e+10 | E23: =1-E22 -> 0 | F23: =E23*B16 -> 0 | G23: =1-G22 -> 1 | H23: =G23*B16 -> 1.5952569e+11 | K23: P/E ratio | L23: =L12 -> 33.135495 | M23: =M12 -> 44.803589
K24: EPS Next year | L24: =L22/L23 -> 248.91736 | M24: =M22/M23 -> 11.673172 | N24: =N26/N25 -> 245.07781
A25: Exchange ratio without Premium | C25: =C11/C10 -> 0.063409311 | E25: =E11/E10 -> 0.063409311 | G25: =G11/G10 -> 0.063409311 | K25: Shares outstanding | L25: =L13 -> 279179756 | M25: =M13 -> 277194946 | N25: =L25+L29 -> 2.967565e+08
A26: Exchange Ratio with Premium offered | C26: =C13/C10 -> 0.069774491 | E26: =E13/E10 -> 0.069774491 | G26: =G13/G10 -> 0.069774491 | K26: Net Income next years | L26: =L10 -> 6.9492688e+10 | M26: =M10 -> 3.2357443e+09 | N26: =L26+M26 -> 7.2728433e+10
A27: Number of shares issued in mn | C27: =C26*C14*0.5 -> 9670568.1 | E27: =E26*E14 -> 19341136 | G27: =IF(G22>0,(G26*G14),0) -> 0 | K27: Equity Offer value(No. of shares X Offer price) | N27: =M22*M25 -> 144972956758
A28: Deal is Accretive | B28: Accretive | K28: Exchange ratio (Price of Target/Price of Acquirer) | L28: =M22/L22 -> 0.063409311
A29: Deal is Dilutive | B29: Dilutive | K29: New shares issued to Target Firm SHs | L29: =L28*M25 -> 17576741
K30: Total shares Of combined firm, Post M&A | N30: =L25+L29 -> 2.967565e+08
K31: Net Income of combined firm post M&A | N31: =L26+M26 -> 7.2728433e+10
K32: EPS of combine firm post M&A | N32: =N31/N30 -> 245.07781
A33: Income statement of Acquirer Post M&A | K33: EPS of Acquirer firm Before M&A | N33: =L24 -> 248.91736
A34: Operating Profit - EBIT of Acquirer before M&A | B34: =Valuation!F14*10000000 -> 8.24723e+10 | K34: Accretion(dilution) % to Acquirer post M&A | N34: =N24/L24-1 -> -0.015425001
A35: Operating Profit- EBIT of Target | B35: =[1]Valuation!$F$14*10000000 -> 2646200000
A36: Operating Synergies gained from Merger | B36: =300*10000000 -> 3000000000
A37: Total Operating Profit Of acquirer Post M&A | B37: =SUM(B34:B36) -> 8.81185e+10
A38: Depreciation from write up | B38: 0
A39: Amortization from writeup | B39: 0 | K39: Scenario-2
A40: New Debt interest Expense | B40: 0 | K40: Acquirer acquires target firm at Market price and pays through stock
A41: New debt Interest rate | B41: 0.05 | K41: P/E ratio of Target > P/E ratio of Acquirer
A42: Existing debt interest rate | B42: 0.05 | K42: Exchange ratio more than one
A43: Earnings before tax | B43: =B37-B38-B39-B40 -> 8.81185e+10 | K43: Increase in Net income due to synergy Gains
A44: Tax expense @26% | B44: 0.26 | L44: Acquirer | M44: Target | N44: Combined
A45: Tax Charged | B45: =B44*B43 -> 2.291081e+10 | K45: Share price before announcement | L45: =L9 -> 8248 | M45: =N9 -> 523
A46: Acquirer's Net Income Post M&A | B46: =B43-B45 -> 6.520769e+10 | K46: P/E ratio | L46: =L45/L47 -> 33.135495 | M46: =M45/M47 -> 44.803589
A47: Acquirer's Net Income before M&A | B47: =B34*(1-26%) -> 6.1029502e+10 | K47: EPS Next year | L47: =L49/L48 -> 248.91736 | M47: =M49/M48 -> 11.673172 | N47: =N49/N48 -> 245.07781
K48: Shares outstanding | L48: =L13 -> 279179756 | M48: =N13 -> 277194946 | N48: =N53 -> 2.967565e+08
A49: Assumptions | K49: Net Income next years | L49: =L10 -> 6.9492688e+10 | M49: =N10 -> 3.2357443e+09 | N49: =N54 -> 7.2728433e+10
A50: Acquirer fully diluted shares | B50: =B15 -> 279179756 | K50: Equity Offer value(No. of shares X Offer price) | N50: =M45*M48 -> 144972956758
A51: New shares issued to Target shareholders | B51: =B27 -> 0 | K51: Exchange ratio (Price of Target/Price of Acquirer) | L51: =M45/L45 -> 0.063409311
A52: Total shares of Acquirer post M&A deal | B52: =B50+B51 -> 279179756 | K52: New shares issued to Target Firm SHs | L52: =L51*M48 -> 17576741
A53: Growth rate expected in EBIT of Acquirer post M&A | B53: 0.1 | K53: Total shares Of combined firm, Post M&A | N53: =L52+L48 -> 2.967565e+08
A54: Growth rate expected in EBIT of Acquirer Before M&A | B54: 0.075 | K54: Net Income of combined firm post M&A | N54: =L49+M49 -> 7.2728433e+10
A55: New debt repaid @ 10.5% of outsanding value p.a. | B55: 0.105 | K55: Increase in Net income due to synergy gains | L55: =N14 -> 1500000000
A56: Existing debt repaid at 5% of outsanding value p.a. | B56: 0.05 | K56: Net Income of combined firm adjusted with synergy gain | N56: =N54+L55 -> 7.4228433e+10
K57: EPS of combine firm post M&A | N57: =N56/N53 -> 250.13246
K58: EPS of Acquirer firm Before M&A | N58: =L47 -> 248.91736
A59: SCENARIO 1: 50% STOCK PAYMENT | K59: Accretion(dilution) % to Acquirer post M&A | N59: =N57/N58-1 -> 0.0048815341
A60: Forecasted Income statement of acquirer post M&A | B60: 20X1 | C60: 20X2 | D60: 20X3 | E60: 20X4 | F60: 20X5 | G60: 20X6
A61: Operating Profit - EBIT of Acquirer before M&A | B61: =B34 -> 8.24723e+10 | C61: =B61*(1+$B$65) -> 9.071953e+10 | D61: =C61*(1+$B$65) -> 9.9791483e+10 | E61: =D61*(1+$B$65) -> 1.0977063e+11 | F61: =E61*(1+$B$65) -> 1.2074769e+11 | G61: =F61*(1+$B$65) -> 1.3282246e+11
A62: Operating Profit- EBIT of Target | B62: =B35 -> 2646200000
A63: Operating Synergies gained from Merger | B63: =B36 -> 3000000000 | K63: Scenario-3
A64: Total Operating Profit Of acquirer Post M&A | B64: =SUM(B61:B63) -> 8.81185e+10 | C64: =B64*(1+$B$65) -> 9.693035e+10 | D64: =C64*(1+$B$65) -> 1.0662339e+11 | E64: =D64*(1+$B$65) -> 1.1728572e+11 | F64: =E64*(1+$B$65) -> 1.290143e+11 | G64: =F64*(1+$B$65) -> 1.4191573e+11 | K64: Acquirer acquires target firm at Preium over market price and pays through stock
A65: Growth rate expected in EBIT of Acquirer post M&A | B65: =B53 -> 0.1 | K65: P/E ratio of Target > P/E ratio of Acquirer
A66: Depreciation from write up | B66: =B38 -> 0 | C66: =B66 -> 0 | D66: =C66 -> 0 | E66: =D66 -> 0 | F66: =E66 -> 0 | G66: =F66 -> 0 | K66: Exchange ratio more than one
A67: Amortization from writeup | B67: =B39 -> 0 | C67: =B67 -> 0 | D67: =C67 -> 0 | E67: =D67 -> 0 | F67: =E67 -> 0 | G67: =F67 -> 0 | K67: Offers premium on share price(paid through stock)
A68: Existing interest Expense | B68: =B40 -> 0 | C68: =B68*(1-$D$70) -> 0 | D68: =C68*(1-$D$70) -> 0 | E68: =D68*(1-$D$70) -> 0 | F68: =E68*(1-$D$70) -> 0 | G68: =F68*(1-$D$70) -> 0 | L68: Acquirer | M68: Target | N68: Combined
A69: Existing debt repaid at 5% of outsanding value p.a. | B69: =B56 -> 0.05 | K69: 100% Acquistion of target with stock | N69: No premium | O69: With premium
A70: New debt Interest rate | B70: =B41 -> 0.05 | O70: INR 52.47 /share
A71: New debt Interest Expense @5% | B71: =B70*D230 -> 0 | C71: =C70*E230 -> 0 | D71: =D70*F230 -> 0 | E71: =E70*G230 -> 0 | F71: =F70*H230 -> 0 | G71: =G70*I230 -> 0 | K71: Share price before announcement | L71: =L9 -> 8248 | M71: =M9 -> 523 | N71: =M71 -> 523 | O71: =O9 -> 575.47372
A72: New debt repaid @ 10.5% of outsanding value p.a. | B72: =B55 -> 0.105 | K72: P/E ratio | L72: =L71/L73 -> 33.135495 | M72: =M71/M73 -> 44.803589
A73: Earnings before tax | B73: =B64-B66-B67-B68-B71 -> 8.81185e+10 | C73: =C64-C66-C67-C68-C71 -> 9.693035e+10 | D73: =D64-D66-D67-D68-D71 -> 1.0662339e+11 | E73: =E64-E66-E67-E68-E71 -> 1.1728572e+11 | F73: =F64-F66-F67-F68-F71 -> 1.290143e+11 | G73: =G64-G66-G67-G68-G71 -> 1.4191573e+11 | K73: EPS Next year | L73: =L75/L74 -> 248.91736 | M73: =M75/M74 -> 11.673172 | N73: =N75/N74 -> 245.07781 | O73: =O75/O74 -> 243.63001
A74: Tax expense @26% | B74: =B73*26% -> 2.291081e+10 | C74: =C73*26% -> 2.5201891e+10 | D74: =D73*26% -> 2.772208e+10 | E74: =E73*26% -> 3.0494288e+10 | F74: =F73*26% -> 3.3543717e+10 | G74: =G73*26% -> 3.6898089e+10 | K74: Shares outstanding | L74: =L13 -> 279179756 | M74: =M13 -> 277194946 | N74: =L74+N78 -> 2.967565e+08 | O74: =L74+O78 -> 2.9852001e+08
A75: Acquirer's Net Income Post M&A | B75: =B73-B74 -> 6.520769e+10 | C75: =C73-C74 -> 7.1728459e+10 | D75: =D73-D74 -> 7.8901305e+10 | E75: =E73-E74 -> 8.6791435e+10 | F75: =F73-F74 -> 9.5470579e+10 | G75: =G73-G74 -> 1.0501764e+11 | K75: Net Income | L75: =L10 -> 6.9492688e+10 | M75: =M10 -> 3.2357443e+09 | N75: =L75+M75 -> 7.2728433e+10 | O75: =N75 -> 7.2728433e+10
A76: Acquirer's Net Income without M&A | B76: =B61*(1-26%) -> 6.1029502e+10 | C76: =B76*(1.075) -> 6.5606715e+10 | D76: =C76*(1.075) -> 7.0527218e+10 | E76: =D76*(1.075) -> 7.581676e+10 | F76: =E76*(1.075) -> 8.1503017e+10 | G76: =F76*(1.075) -> 8.7615743e+10 | K76: Equity Offer value(No. of shares X Offer price) | N76: =N71*M74 -> 144972956758 | O76: =O71*M74 -> 1.5951841e+11
A77: Growth rate in EBIT of Acquirer without M&A | B77: =B54 -> 0.075 | K77: Exchange ratio (Price of Target/Price of Acquirer) | N77: =N71/L71 -> 0.063409311 | O77: =O71/L71 -> 0.069771304
A78: Acquirer fully diluted shares | B78: =B15 -> 279179756 | C78: =B78 -> 279179756 | D78: =C78 -> 279179756 | E78: =D78 -> 279179756 | F78: =E78 -> 279179756 | G78: =F78 -> 279179756 | K78: New shares issued to Target Firm SHs | N78: =N77*M74 -> 17576741 | O78: =O77*M74 -> 19340253
A79: New shares issued to Target shareholders | B79: =C27 -> 9670568.1 | C79: =B79 -> 9670568.1 | D79: =C79 -> 9670568.1 | E79: =D79 -> 9670568.1 | F79: =E79 -> 9670568.1 | G79: =F79 -> 9670568.1 | K79: Total shares Of combined firm, Post M&A | N79: =L74+N78 -> 2.967565e+08 | O79: =L74+O78 -> 2.9852001e+08
A80: Total shares post M&A deal | B80: =B78+B79 -> 2.8885032e+08 | C80: =C78+C79 -> 2.8885032e+08 | D80: =D78+D79 -> 2.8885032e+08 | E80: =E78+E79 -> 2.8885032e+08 | F80: =F78+F79 -> 2.8885032e+08 | G80: =G78+G79 -> 2.8885032e+08 | K80: Net Income of combined firm post M&A | N80: =L75+M75 -> 7.2728433e+10 | O80: =N80 -> 7.2728433e+10
K81: Increase in Net income due to synergy gains | N81: =O14 -> 0 | O81: =O14 -> 0
A82: Acquirer's Diluted EPS post M&A | B82: =B75/B80 -> 225.74906 | C82: =C75/C80 -> 248.32397 | D82: =D75/D80 -> 273.15637 | E82: =E75/E80 -> 300.472 | F82: =F75/F80 -> 330.5192 | G82: =G75/G80 -> 363.57112 | K82: Net Income of combined firm adjusted with synergy gain | N82: =N80+N81 -> 7.2728433e+10 | O82: =O80+O81 -> 7.2728433e+10
A83: Acquirer diluted EPS before M&A | B83: =B76/B78 -> 218.60289 | C83: =C76/C78 -> 234.99811 | D83: =D76/D78 -> 252.62297 | E83: =E76/E78 -> 271.56969 | F83: =F76/F78 -> 291.93742 | G83: =G76/G78 -> 313.83272 | K83: EPS of combine firm post M&A | N83: =N82/N79 -> 245.07781 | O83: =O82/O79 -> 243.63001
K84: EPS of Acquirer firm Before M&A | N84: =L73 -> 248.91736 | O84: =N84 -> 248.91736
A85: Accretion/Dilution-INR | B85: =B82-B83 -> 7.1461711 | C85: =C82-C83 -> 13.325861 | D85: =D82-D83 -> 20.533399 | E85: =E82-E83 -> 28.902313 | F85: =F82-F83 -> 38.581787 | G85: =G82-G83 -> 49.738401 | K85: Accretion(dilution) % to Acquirer post M&A | N85: =N83/N84-1 -> -0.015425001 | O85: =O83/O84-1 -> -0.021241396
A86: Accretion/Dilution-% | B86: =B82/B83-1 -> 0.032690195 | C86: =C82/C83-1 -> 0.056706246 | D86: =D82/D83-1 -> 0.08128081 | E86: =E82/E83-1 -> 0.10642688 | F86: =F82/F83-1 -> 0.13215773 | G86: =G82/G83-1 -> 0.15848698
A87: Accretive /Dilutive | B87: =IF(B86>0,$D$29,$D$30) -> 0 | C87: =IF(C86>0,$D$29,$D$30) -> 0 | D87: =IF(D86>0,$D$29,$D$30) -> 0 | E87: =IF(E86>0,$D$29,$D$30) -> 0 | F87: =IF(F86>0,$D$29,$D$30) -> 0 | G87: =IF(G86>0,$D$29,$D$30) -> 0
K89: Scenario-4
K90: Acquirer acquires target firm with 50% cash and 50% stock payment
A91: SCENARIO 2: 100% STOCK PAYMENT | K91: P/E ratio of Target > P/E ratio of Acquirer
K92: Exchange ratio more than one
A93: Forecasted Income statement of acquirer post M&A | B93: 20X1 | C93: 20X2 | D93: 20X3 | E93: 20X4 | F93: 20X5 | G93: 20X6 | K93: Offers premium on share price(paid through stock)
A94: Operating Profit - EBIT of Acquirer before M&A | B94: =B34 -> 8.24723e+10 | C94: =B94*(1+$B$98) -> 9.071953e+10 | D94: =C94*(1+$B$98) -> 9.9791483e+10 | E94: =D94*(1+$B$98) -> 1.0977063e+11 | F94: =E94*(1+$B$98) -> 1.2074769e+11 | G94: =F94*(1+$B$98) -> 1.3282246e+11 | L94: Acquirer | M94: Target | N94: Combined no premium
A95: Operating Profit- EBIT of Target | B95: =B35 -> 2646200000 | K95: 100% Acquistion of target with stock | P95: With premium
A96: Operating Synergies gained from Merger | B96: =B36 -> 3000000000 | P96: INR 52.47 /share
A97: Total Operating Profit Of acquirer Post M&A | B97: =SUM(B94:B96) -> 8.81185e+10 | C97: =B97*(1+$B$98) -> 9.693035e+10 | D97: =C97*(1+$B$98) -> 1.0662339e+11 | E97: =D97*(1+$B$98) -> 1.1728572e+11 | F97: =E97*(1+$B$98) -> 1.290143e+11 | G97: =F97*(1+$B$98) -> 1.4191573e+11 | N97: 100% stock | O97: 50% stock | P97: 100% stock | Q97: 50% stock
A98: Growth rate expected in EBIT of Acquirer post M&A | B98: =B53 -> 0.1 | K98: Share price before announcement | L98: =L9 -> 8248 | M98: =M9 -> 523 | N98: =M98 -> 523 | O98: =M98 -> 523 | P98: =P9 -> 575.47372 | Q98: =P9 -> 575.47372
A99: Depreciation from write up | B99: =B66 -> 0 | C99: =B99 -> 0 | D99: =C99 -> 0 | E99: =D99 -> 0 | F99: =E99 -> 0 | G99: =F99 -> 0 | K99: P/E ratio | L99: =L98/L100 -> 33.135495 | M99: =M98/M100 -> 44.803589
A100: Amortization from writeup | B100: =B67 -> 0 | C100: =B100 -> 0 | D100: =C100 -> 0 | E100: =D100 -> 0 | F100: =E100 -> 0 | G100: =F100 -> 0 | K100: EPS Next year | L100: =L102/L101 -> 248.91736 | M100: =M102/M101 -> 11.673172 | N100: =N102/N101 -> 245.07781 | O100: =O102/O101 -> 252.55723 | P100: =P102/P101 -> 243.63001 | Q100: =Q102/Q101 -> 251.78626
A101: Existing interest Expense | B101: =B68 -> 0 | C101: =B101*(1-$D$103) -> 0 | D101: =C101*(1-$D$103) -> 0 | E101: =D101*(1-$D$103) -> 0 | F101: =E101*(1-$D$103) -> 0 | G101: =F101*(1-$D$103) -> 0 | K101: Shares outstanding | L101: =L13 -> 279179756 | M101: =M13 -> 277194946 | N101: =N106 -> 2.967565e+08 | O101: =O106 -> 2.8796813e+08 | P101: =P106 -> 2.9852001e+08 | Q101: =Q106 -> 2.8884988e+08
A102: New debt Interest rate | B102: =B41 -> 0.05 | K102: Net Income next years | L102: =L10 -> 6.9492688e+10 | M102: =M10 -> 3.2357443e+09 | N102: =L102+M102 -> 7.2728433e+10 | O102: =N102 -> 7.2728433e+10 | P102: =N102 -> 7.2728433e+10 | Q102: =P102 -> 7.2728433e+10
A103: Existing debt repaid at 5% of outsanding value p.a. | B103: =B56 -> 0.05 | K103: Equity Offer value(No. of shares X Offer price) | N103: =N98*M101 -> 144972956758 | O103: =O98*M101 -> 144972956758 | P103: =P98*M101 -> 1.5951841e+11 | Q103: =Q98*M101 -> 1.5951841e+11
A104: New debt Interest Expense @5% | B104: =$D$104*$H$24 -> 0 | C104: =$D$104*$H$24 -> 0 | D104: =$D$104*$H$24 -> 0 | E104: =$D$104*$H$24 -> 0 | F104: =$D$104*$H$24 -> 0 | G104: =$D$104*$H$24 -> 0 | K104: Exchange ratio (Price of Target/Price of Acquirer) | N104: =N98/L98 -> 0.063409311 | O104: =O98/L98 -> 0.063409311 | P104: =P98/L98 -> 0.069771304 | Q104: =Q98/L98 -> 0.069771304
...

Sheet Synergy
A1: Synergy Area | B1: Basis | C1: FY25 Estimate (INR Cr) | D1: FY26 | E1: FY27 | F1: Notes
A2: Export of HBL products via Bajaj channels | B2: Assume 5% of HBL’s forecasted revenue (₹2,932 Cr in 2026) in new markets | C2: 150 | D2: 200 | E2: 250 | F2: Based on gradual market penetration
A3: Bundled EV battery sales | B3: ₹10K avg margin per EV, 1 lakh units | C3: 100 | D3: 120 | E3: 150 | F3: Based on projected EV growth
A4: Distribution cost savings | B4: 2% of combined COGS | C4: 50 | D4: 60 | E4: 70 | F4: Shared channels, logistics
A5: Total Annual Revenue/Cost Synergy | C5: 300 | D5: 380 | E5: 470
A7: WACC for combined entity | B7: 8.5% to 9%
A8: in crores | B8: =NPV(8.5%,C8:E8) -> 967.25751 | C8: =300 -> 300 | D8: =380 -> 380 | E8: =470 -> 470
A10: synergy value | B10: =B8*10000000 -> 9.6725751e+09
